clusterking/__init__.py
clusterking/conftest.py
clusterking/git_info.json
clusterking/result.py
clusterking/version.txt
clusterking/worker.py
clusterking/benchmark/__init__.py
clusterking/benchmark/abstract_benchmark.py
clusterking/benchmark/benchmark.py
clusterking/benchmark/test/__init__.py
clusterking/benchmark/test/test_benchmark.py
clusterking/cluster/__init__.py
clusterking/cluster/cluster.py
clusterking/cluster/hierarchy_cluster.py
clusterking/cluster/kmeans_cluster.py
clusterking/cluster/test/__init__.py
clusterking/cluster/test/test_hierarchy_cluster.py
clusterking/cluster/test/test_kmeans_cluster.py
clusterking/data/__init__.py
clusterking/data/data.py
clusterking/data/dfmd.py
clusterking/data/dwe.py
clusterking/maths/__init__.py
clusterking/maths/binning.py
clusterking/maths/metric.py
clusterking/maths/metric_utils.py
clusterking/maths/statistics.py
clusterking/plots/__init__.py
clusterking/plots/colors.py
clusterking/plots/plot_bundles.py
clusterking/plots/plot_clusters.py
clusterking/plots/plot_histogram.py
clusterking/plots/test/__init__.py
clusterking/plots/test/test_plot_histogram.py
clusterking/scan/__init__.py
clusterking/scan/scanner.py
clusterking/scan/wilsonscanner.py
clusterking/scan/test/__init__.py
clusterking/scan/test/test_scanner.py
clusterking/scan/test/test_wilsonscanner.py
clusterking/stability/__init__.py
clusterking/stability/fom.py
clusterking/stability/noisysamplestability.py
clusterking/stability/preprocessor.py
clusterking/stability/stabilitytester.py
clusterking/stability/subsamplestability.py
clusterking/stability/test/__init__.py
clusterking/stability/test/test_fom.py
clusterking/stability/test/test_noisysamplestability.py
clusterking/stability/test/test_preprocessor.py
clusterking/stability/test/test_subsamplestability.py
clusterking/test/__init__.py
clusterking/test/test_integration.py
clusterking/util/__init__.py
clusterking/util/cli.py
clusterking/util/log.py
clusterking/util/matplotlib_utils.py
clusterking-1.1.0.dist-info/LICENSE.txt
clusterking-1.1.0.dist-info/METADATA
clusterking-1.1.0.dist-info/WHEEL
clusterking-1.1.0.dist-info/top_level.txt
clusterking-1.1.0.dist-info/RECORD
