Metadata-Version: 2.1
Name: clusterking
Version: 1.1.0
Summary: Cluster sets of histograms/curves, in particular kinematic distributions in high energy physics.
Home-page: https://github.com/clusterking/clusterking
License: MIT
Project-URL: Bug Tracker, https://github.com/clusterking/clusterking/issues
Project-URL: Documentation, https://clusterking.readthedocs.io/
Project-URL: Source Code, https://github.com/clusterking/clusterking/
Keywords: clustering,cluster,kinematics,cluster-analysis,machine-learning,ml,hep,hep-ml,hep-ex,hep-ph,wilson
Platform: UNKNOWN
Classifier: Programming Language :: Python :: 3
Classifier: License :: OSI Approved :: MIT License
Classifier: Operating System :: OS Independent
Classifier: Topic :: Scientific/Engineering :: Physics
Classifier: Topic :: Scientific/Engineering :: Visualization
Requires-Dist: colorlog
Requires-Dist: gitpython
Requires-Dist: numpy
Requires-Dist: pandas
Requires-Dist: scipy
Requires-Dist: sklearn
Requires-Dist: sqlalchemy
Requires-Dist: tqdm
Requires-Dist: wilson
Provides-Extra: dev
Requires-Dist: coveralls ; extra == 'dev'
Requires-Dist: ipykernel ; extra == 'dev'
Requires-Dist: jupyter-client ; extra == 'dev'
Requires-Dist: nbconvert ; extra == 'dev'
Requires-Dist: nbformat ; extra == 'dev'
Requires-Dist: nbstripout ; extra == 'dev'
Requires-Dist: pre-commit ; extra == 'dev'
Requires-Dist: pytest-cov ; extra == 'dev'
Requires-Dist: pytest-subtests ; extra == 'dev'
Requires-Dist: pytest (>=4.4.0) ; extra == 'dev'
Requires-Dist: sphinx ; extra == 'dev'
Requires-Dist: sphinx-rtd-theme ; extra == 'dev'
Requires-Dist: twine ; extra == 'dev'
Provides-Extra: plotting
Requires-Dist: matplotlib ; extra == 'plotting'
